{
  "descriptionHash": "FA3621395C5CCB11A82FCF10E170BABC719F26E9C3D776068B2A2664F6C144C287CB515BDA233E23BDFE8354EB3A3FDE36535D146B703837A9D792922572386E",
  "descriptionLocation": "../RoriaSharp/openapi.json",
  "lockFileVersion": "1.0.0",
  "kiotaVersion": "1.30.0",
  "clientClassName": "ApiClient",
  "typeAccessModifier": "Public",
  "clientNamespaceName": "RoriaSharp.Api",
  "language": "CSharp",
  "usesBackingStore": false,
  "excludeBackwardCompatible": false,
  "includeAdditionalData": true,
  "disableSSLValidation": false,
  "serializers": [
    "Microsoft.Kiota.Serialization.Json.JsonSerializationWriterFactory",
    "Microsoft.Kiota.Serialization.Text.TextSerializationWriterFactory",
    "Microsoft.Kiota.Serialization.Form.FormSerializationWriterFactory",
    "Microsoft.Kiota.Serialization.Multipart.MultipartSerializationWriterFactory"
  ],
  "deserializers": [
    "Microsoft.Kiota.Serialization.Json.JsonParseNodeFactory",
    "Microsoft.Kiota.Serialization.Text.TextParseNodeFactory",
    "Microsoft.Kiota.Serialization.Form.FormParseNodeFactory"
  ],
  "structuredMimeTypes": [
    "application/json",
    "text/plain;q=0.9",
    "application/x-www-form-urlencoded;q=0.2",
    "multipart/form-data;q=0.1"
  ],
  "includePatterns": [],
  "excludePatterns": [],
  "disabledValidationRules": []
}